parser/__init__.py
parser/combined.py
vn_address-0.2.data/scripts/vnas
vn_address-0.2.dist-info/LICENSE
vn_address-0.2.dist-info/METADATA
vn_address-0.2.dist-info/WHEEL
vn_address-0.2.dist-info/top_level.txt
vn_address-0.2.dist-info/RECORD
